opentelemetry/instrumentation/aerospike/__init__.py
opentelemetry/instrumentation/aerospike/package.py
opentelemetry/instrumentation/aerospike/version.py
opentelemetry_instrumentation_aerospike-0.2.4.dist-info/METADATA
opentelemetry_instrumentation_aerospike-0.2.4.dist-info/WHEEL
opentelemetry_instrumentation_aerospike-0.2.4.dist-info/entry_points.txt
opentelemetry_instrumentation_aerospike-0.2.4.dist-info/licenses/LICENSE
opentelemetry_instrumentation_aerospike-0.2.4.dist-info/RECORD
