Metadata-Version: 2.4
Name: opentelemetry-instrumentation-aerospike
Version: 0.2.4
Summary: OpenTelemetry Aerospike instrumentation
Project-URL: Homepage, https://github.com/KimSoungRyoul/opentelemetry-instrumentation-aerospike
Project-URL: Repository, https://github.com/KimSoungRyoul/opentelemetry-instrumentation-aerospike
Project-URL: Documentation, https://github.com/KimSoungRyoul/opentelemetry-instrumentation-aerospike#readme
Author-email: kimsoungryoul <soungryoul.kim@navercorp.com>
License-Expression: Apache-2.0
License-File: LICENSE
Keywords: aerospike,instrumentation,observability,opentelemetry,tracing
Classifier: Development Status :: 4 - Beta
Classifier: Intended Audience :: Developers
Classifier: License :: OSI Approved :: Apache Software License
Classifier: Programming Language :: Python
Classifier: Programming Language :: Python :: 3
Classifier: Programming Language :: Python :: 3.10
Classifier: Programming Language :: Python :: 3.11
Classifier: Programming Language :: Python :: 3.12
Classifier: Programming Language :: Python :: 3.13
Classifier: Topic :: Software Development :: Libraries :: Python Modules
Classifier: Topic :: System :: Monitoring
Requires-Python: >=3.10
Requires-Dist: opentelemetry-api~=1.12
Requires-Dist: opentelemetry-instrumentation>=0.40b0
Requires-Dist: opentelemetry-semantic-conventions>=0.40b0
Requires-Dist: wrapt<2.0.0,>=1.0.0
Provides-Extra: dev
Requires-Dist: aerospike>=17.0.0; extra == 'dev'
Requires-Dist: black>=23.0; extra == 'dev'
Requires-Dist: isort>=5.0; extra == 'dev'
Requires-Dist: mypy>=1.0; extra == 'dev'
Requires-Dist: opentelemetry-sdk>=1.12; extra == 'dev'
Requires-Dist: opentelemetry-test-utils>=0.40b0; extra == 'dev'
Requires-Dist: pytest-cov>=4.0; extra == 'dev'
Requires-Dist: pytest>=7.0; extra == 'dev'
Requires-Dist: ruff>=0.1.0; extra == 'dev'
Provides-Extra: instruments
Requires-Dist: aerospike>=17.0.0; extra == 'instruments'
Provides-Extra: test
Requires-Dist: aerospike>=17.0.0; extra == 'test'
Requires-Dist: opentelemetry-sdk>=1.12; extra == 'test'
Requires-Dist: opentelemetry-test-utils>=0.40b0; extra == 'test'
Requires-Dist: pytest-cov>=4.0; extra == 'test'
Requires-Dist: pytest>=7.0; extra == 'test'
